{"design__instance__count": 629, "design__instance__area": 5177.47, "design__instance_unmapped__count": 0, "synthesis__check_error__count": 0, "design__max_slew_violation__count__corner:nom_tt_025C_1v80": 0, "design__max_fanout_violation__count__corner:nom_tt_025C_1v80": 4, "design__max_cap_violation__count__corner:nom_tt_025C_1v80": 0, "power__internal__total": 7.981041562743485e-05, "power__switching__total": 3.347134042996913e-05, "power__leakage__total": 5.094455080012494e-09, "power__total": 0.00011328684922773391, "clock__skew__worst_hold__corner:nom_tt_025C_1v80": -1.441808, "clock__skew__worst_setup__corner:nom_tt_025C_1v80": -1.439007, "timing__hold__ws__corner:nom_tt_025C_1v80": 0.232165, "timing__setup__ws__corner:nom_tt_025C_1v80": 1.289282, "timing__hold__tns__corner:nom_tt_025C_1v80": 0.0, "timing__setup__tns__corner:nom_tt_025C_1v80": 0.0, "timing__hold__wns__corner:nom_tt_025C_1v80": 0.0, "timing__setup__wns__corner:nom_tt_025C_1v80": 0.0, "timing__hold_vio__count__corner:nom_tt_025C_1v80": 0, "timing__hold_r2r__ws__corner:nom_tt_025C_1v80": 0.232165, "timing__hold_r2r_vio__count__corner:nom_tt_025C_1v80": 0, "timing__setup_vio__count__corner:nom_tt_025C_1v80": 0, "timing__setup_r2r__ws__corner:nom_tt_025C_1v80": 1.289282, "timing__setup_r2r_vio__count__corner:nom_tt_025C_1v80": 0, "design__max_slew_violation__count__corner:nom_ss_100C_1v60": 133, "design__max_fanout_violation__count__corner:nom_ss_100C_1v60": 4, "design__max_cap_violation__count__corner:nom_ss_100C_1v60": 2, "clock__skew__worst_hold__corner:nom_ss_100C_1v60": -2.675106, "clock__skew__worst_setup__corner:nom_ss_100C_1v60": -2.670122, "timing__hold__ws__corner:nom_ss_100C_1v60": 0.65519, "timing__setup__ws__corner:nom_ss_100C_1v60": 0.200934, "timing__hold__tns__corner:nom_ss_100C_1v60": 0.0, "timing__setup__tns__corner:nom_ss_100C_1v60": 0.0, "timing__hold__wns__corner:nom_ss_100C_1v60": 0.0, "timing__setup__wns__corner:nom_ss_100C_1v60": 0.0, "timing__hold_vio__count__corner:nom_ss_100C_1v60": 0, "timing__hold_r2r__ws__corner:nom_ss_100C_1v60": 0.65519, "timing__hold_r2r_vio__count__corner:nom_ss_100C_1v60": 0, "timing__setup_vio__count__corner:nom_ss_100C_1v60": 0, "timing__setup_r2r__ws__corner:nom_ss_100C_1v60": 0.200934, "timing__setup_r2r_vio__count__corner:nom_ss_100C_1v60": 0, "design__max_slew_violation__count__corner:nom_ff_n40C_1v95": 0, "design__max_fanout_violation__count__corner:nom_ff_n40C_1v95": 4, "design__max_cap_violation__count__corner:nom_ff_n40C_1v95": 0, "clock__skew__worst_hold__corner:nom_ff_n40C_1v95": -0.758671, "clock__skew__worst_setup__corner:nom_ff_n40C_1v95": -0.752254, "timing__hold__ws__corner:nom_ff_n40C_1v95": 0.086556, "timing__setup__ws__corner:nom_ff_n40C_1v95": 1.484074, "timing__hold__tns__corner:nom_ff_n40C_1v95": 0.0, "timing__setup__tns__corner:nom_ff_n40C_1v95": 0.0, "timing__hold__wns__corner:nom_ff_n40C_1v95": 0.0, "timing__setup__wns__corner:nom_ff_n40C_1v95": 0.0, "timing__hold_vio__count__corner:nom_ff_n40C_1v95": 0, "timing__hold_r2r__ws__corner:nom_ff_n40C_1v95": 0.086556, "timing__hold_r2r_vio__count__corner:nom_ff_n40C_1v95": 0, "timing__setup_vio__count__corner:nom_ff_n40C_1v95": 0, "timing__setup_r2r__ws__corner:nom_ff_n40C_1v95": 1.484074, "timing__setup_r2r_vio__count__corner:nom_ff_n40C_1v95": 0, "design__max_slew_violation__count": 133, "design__max_fanout_violation__count": 4, "design__max_cap_violation__count": 2, "clock__skew__worst_hold": -0.753696, "clock__skew__worst_setup": -2.679138, "timing__hold__ws": 0.074949, "timing__setup__ws": 0.154515, "timing__hold__tns": 0.0, "timing__setup__tns": 0.0, "timing__hold__wns": 0.0, "timing__setup__wns": 0.0, "timing__hold_vio__count": 0, "timing__hold_r2r__ws": 0.074949, "timing__hold_r2r_vio__count": 0, "timing__setup_vio__count": 0, "timing__setup_r2r__ws": 0.154515, "timing__setup_r2r_vio__count": 0, "design__die__bbox": "0.0 0.0 108.26 118.98", "design__core__bbox": "5.52 10.88 102.58 106.08", "flow__warnings__count": 1, "flow__errors__count": 0, "design__io": 19, "design__die__area": 12880.8, "design__core__area": 9240.11, "design__instance__count__stdcell": 629, "design__instance__area__stdcell": 5177.47, "design__instance__count__macros": 0, "design__instance__area__macros": 0, "design__instance__utilization": 0.560325, "design__instance__utilization__stdcell": 0.560325, "design__power_grid_violation__count__net:vssd1": 0, "design__power_grid_violation__count__net:vccd1": 0, "design__power_grid_violation__count": 0, "floorplan__design__io": 17, "design__io__hpwl": 753874, "timing__drv__floating__nets": 0, "timing__drv__floating__pins": 0, "design__instance__displacement__total": 0, "design__instance__displacement__mean": 0, "design__instance__displacement__max": 0, "route__wirelength__estimated": 5298.2, "design__violations": 0, "design__instance__count__setup_buffer": 0, "design__instance__count__hold_buffer": 0, "antenna__violating__nets": 0, "antenna__violating__pins": 0, "route__antenna_violation__count": 0, "route__net": 369, "route__net__special": 2, "route__drc_errors__iter:1": 151, "route__wirelength__iter:1": 6225, "route__drc_errors__iter:2": 18, "route__wirelength__iter:2": 6131, "route__drc_errors__iter:3": 6, "route__wirelength__iter:3": 6117, "route__drc_errors__iter:4": 0, "route__wirelength__iter:4": 6139, "route__drc_errors": 0, "route__wirelength": 6139, "route__vias": 2479, "route__vias__singlecut": 2479, "route__vias__multicut": 0, "design__disconnected_pin__count": 0, "design__critical_disconnected_pin__count": 0, "route__wirelength__max": 640.02, "timing__unannotated_net__count__corner:nom_tt_025C_1v80": 1, "timing__unannotated_net_filtered__count__corner:nom_tt_025C_1v80": 0, "timing__unannotated_net__count__corner:nom_ss_100C_1v60": 1, "timing__unannotated_net_filtered__count__corner:nom_ss_100C_1v60": 0, "timing__unannotated_net__count__corner:nom_ff_n40C_1v95": 1, "timing__unannotated_net_filtered__count__corner:nom_ff_n40C_1v95": 0, "design__max_slew_violation__count__corner:min_tt_025C_1v80": 0, "design__max_fanout_violation__count__corner:min_tt_025C_1v80": 4, "design__max_cap_violation__count__corner:min_tt_025C_1v80": 0, "clock__skew__worst_hold__corner:min_tt_025C_1v80": -1.4339, "clock__skew__worst_setup__corner:min_tt_025C_1v80": -1.431164, "timing__hold__ws__corner:min_tt_025C_1v80": 0.235205, "timing__setup__ws__corner:min_tt_025C_1v80": 1.315136, "timing__hold__tns__corner:min_tt_025C_1v80": 0.0, "timing__setup__tns__corner:min_tt_025C_1v80": 0.0, "timing__hold__wns__corner:min_tt_025C_1v80": 0.0, "timing__setup__wns__corner:min_tt_025C_1v80": 0.0, "timing__hold_vio__count__corner:min_tt_025C_1v80": 0, "timing__hold_r2r__ws__corner:min_tt_025C_1v80": 0.235205, "timing__hold_r2r_vio__count__corner:min_tt_025C_1v80": 0, "timing__setup_vio__count__corner:min_tt_025C_1v80": 0, "timing__setup_r2r__ws__corner:min_tt_025C_1v80": 1.315136, "timing__setup_r2r_vio__count__corner:min_tt_025C_1v80": 0, "timing__unannotated_net__count__corner:min_tt_025C_1v80": 1, "timing__unannotated_net_filtered__count__corner:min_tt_025C_1v80": 0, "design__max_slew_violation__count__corner:min_ss_100C_1v60": 133, "design__max_fanout_violation__count__corner:min_ss_100C_1v60": 4, "design__max_cap_violation__count__corner:min_ss_100C_1v60": 2, "clock__skew__worst_hold__corner:min_ss_100C_1v60": -2.65807, "clock__skew__worst_setup__corner:min_ss_100C_1v60": -2.653069, "timing__hold__ws__corner:min_ss_100C_1v60": 0.663346, "timing__setup__ws__corner:min_ss_100C_1v60": 0.243362, "timing__hold__tns__corner:min_ss_100C_1v60": 0.0, "timing__setup__tns__corner:min_ss_100C_1v60": 0.0, "timing__hold__wns__corner:min_ss_100C_1v60": 0.0, "timing__setup__wns__corner:min_ss_100C_1v60": 0.0, "timing__hold_vio__count__corner:min_ss_100C_1v60": 0, "timing__hold_r2r__ws__corner:min_ss_100C_1v60": 0.663346, "timing__hold_r2r_vio__count__corner:min_ss_100C_1v60": 0, "timing__setup_vio__count__corner:min_ss_100C_1v60": 0, "timing__setup_r2r__ws__corner:min_ss_100C_1v60": 0.243362, "timing__setup_r2r_vio__count__corner:min_ss_100C_1v60": 0, "timing__unannotated_net__count__corner:min_ss_100C_1v60": 1, "timing__unannotated_net_filtered__count__corner:min_ss_100C_1v60": 0, "design__max_slew_violation__count__corner:min_ff_n40C_1v95": 0, "design__max_fanout_violation__count__corner:min_ff_n40C_1v95": 4, "design__max_cap_violation__count__corner:min_ff_n40C_1v95": 0, "clock__skew__worst_hold__corner:min_ff_n40C_1v95": -0.753696, "clock__skew__worst_setup__corner:min_ff_n40C_1v95": -0.747401, "timing__hold__ws__corner:min_ff_n40C_1v95": 0.090236, "timing__setup__ws__corner:min_ff_n40C_1v95": 1.50156, "timing__hold__tns__corner:min_ff_n40C_1v95": 0.0, "timing__setup__tns__corner:min_ff_n40C_1v95": 0.0, "timing__hold__wns__corner:min_ff_n40C_1v95": 0.0, "timing__setup__wns__corner:min_ff_n40C_1v95": 0.0, "timing__hold_vio__count__corner:min_ff_n40C_1v95": 0, "timing__hold_r2r__ws__corner:min_ff_n40C_1v95": 0.090236, "timing__hold_r2r_vio__count__corner:min_ff_n40C_1v95": 0, "timing__setup_vio__count__corner:min_ff_n40C_1v95": 0, "timing__setup_r2r__ws__corner:min_ff_n40C_1v95": 1.50156, "timing__setup_r2r_vio__count__corner:min_ff_n40C_1v95": 0, "timing__unannotated_net__count__corner:min_ff_n40C_1v95": 1, "timing__unannotated_net_filtered__count__corner:min_ff_n40C_1v95": 0, "design__max_slew_violation__count__corner:max_tt_025C_1v80": 0, "design__max_fanout_violation__count__corner:max_tt_025C_1v80": 4, "design__max_cap_violation__count__corner:max_tt_025C_1v80": 0, "clock__skew__worst_hold__corner:max_tt_025C_1v80": -1.442436, "clock__skew__worst_setup__corner:max_tt_025C_1v80": -1.439655, "timing__hold__ws__corner:max_tt_025C_1v80": 0.220766, "timing__setup__ws__corner:max_tt_025C_1v80": 1.257427, "timing__hold__tns__corner:max_tt_025C_1v80": 0.0, "timing__setup__tns__corner:max_tt_025C_1v80": 0.0, "timing__hold__wns__corner:max_tt_025C_1v80": 0.0, "timing__setup__wns__corner:max_tt_025C_1v80": 0.0, "timing__hold_vio__count__corner:max_tt_025C_1v80": 0, "timing__hold_r2r__ws__corner:max_tt_025C_1v80": 0.220766, "timing__hold_r2r_vio__count__corner:max_tt_025C_1v80": 0, "timing__setup_vio__count__corner:max_tt_025C_1v80": 0, "timing__setup_r2r__ws__corner:max_tt_025C_1v80": 1.257427, "timing__setup_r2r_vio__count__corner:max_tt_025C_1v80": 0, "timing__unannotated_net__count__corner:max_tt_025C_1v80": 1, "timing__unannotated_net_filtered__count__corner:max_tt_025C_1v80": 0, "design__max_slew_violation__count__corner:max_ss_100C_1v60": 133, "design__max_fanout_violation__count__corner:max_ss_100C_1v60": 4, "design__max_cap_violation__count__corner:max_ss_100C_1v60": 2, "clock__skew__worst_hold__corner:max_ss_100C_1v60": -2.684111, "clock__skew__worst_setup__corner:max_ss_100C_1v60": -2.679138, "timing__hold__ws__corner:max_ss_100C_1v60": 0.639782, "timing__setup__ws__corner:max_ss_100C_1v60": 0.154515, "timing__hold__tns__corner:max_ss_100C_1v60": 0.0, "timing__setup__tns__corner:max_ss_100C_1v60": 0.0, "timing__hold__wns__corner:max_ss_100C_1v60": 0.0, "timing__setup__wns__corner:max_ss_100C_1v60": 0.0, "timing__hold_vio__count__corner:max_ss_100C_1v60": 0, "timing__hold_r2r__ws__corner:max_ss_100C_1v60": 0.639782, "timing__hold_r2r_vio__count__corner:max_ss_100C_1v60": 0, "timing__setup_vio__count__corner:max_ss_100C_1v60": 0, "timing__setup_r2r__ws__corner:max_ss_100C_1v60": 0.154515, "timing__setup_r2r_vio__count__corner:max_ss_100C_1v60": 0, "timing__unannotated_net__count__corner:max_ss_100C_1v60": 1, "timing__unannotated_net_filtered__count__corner:max_ss_100C_1v60": 0, "design__max_slew_violation__count__corner:max_ff_n40C_1v95": 0, "design__max_fanout_violation__count__corner:max_ff_n40C_1v95": 4, "design__max_cap_violation__count__corner:max_ff_n40C_1v95": 0, "clock__skew__worst_hold__corner:max_ff_n40C_1v95": -0.75689, "clock__skew__worst_setup__corner:max_ff_n40C_1v95": -0.750434, "timing__hold__ws__corner:max_ff_n40C_1v95": 0.074949, "timing__setup__ws__corner:max_ff_n40C_1v95": 1.460617, "timing__hold__tns__corner:max_ff_n40C_1v95": 0.0, "timing__setup__tns__corner:max_ff_n40C_1v95": 0.0, "timing__hold__wns__corner:max_ff_n40C_1v95": 0.0, "timing__setup__wns__corner:max_ff_n40C_1v95": 0.0, "timing__hold_vio__count__corner:max_ff_n40C_1v95": 0, "timing__hold_r2r__ws__corner:max_ff_n40C_1v95": 0.074949, "timing__hold_r2r_vio__count__corner:max_ff_n40C_1v95": 0, "timing__setup_vio__count__corner:max_ff_n40C_1v95": 0, "timing__setup_r2r__ws__corner:max_ff_n40C_1v95": 1.460617, "timing__setup_r2r_vio__count__corner:max_ff_n40C_1v95": 0, "timing__unannotated_net__count__corner:max_ff_n40C_1v95": 1, "timing__unannotated_net_filtered__count__corner:max_ff_n40C_1v95": 0, "timing__unannotated_net__count": 1, "timing__unannotated_net_filtered__count": 0, "design_powergrid__voltage__worst__net:vccd1__corner:nom_tt_025C_1v80": 1.79998, "design_powergrid__drop__average__net:vccd1__corner:nom_tt_025C_1v80": 1.8, "design_powergrid__drop__worst__net:vccd1__corner:nom_tt_025C_1v80": 1.68588e-05, "design_powergrid__voltage__worst__net:vssd1__corner:nom_tt_025C_1v80": 1.41742e-05, "design_powergrid__drop__average__net:vssd1__corner:nom_tt_025C_1v80": 2.53173e-06, "design_powergrid__drop__worst__net:vssd1__corner:nom_tt_025C_1v80": 1.41742e-05, "ir__voltage__worst": 1.8, "ir__drop__avg": 2.55e-06, "ir__drop__worst": 1.69e-05, "design__xor_difference__count": 0, "magic__drc_error__count": 0, "klayout__drc_error__count": 0, "magic__illegal_overlap__count": 0, "design__lvs_device_difference__count": 0, "design__lvs_net_difference__count": 0, "design__lvs_property_fail__count": 0, "design__lvs_error__count": 0, "design__lvs_unmatched_device__count": 0, "design__lvs_unmatched_net__count": 0, "design__lvs_unmatched_pin__count": 0}