{"design__instance__count": 630, "design__instance__area": 5187.48, "design__instance_unmapped__count": 0, "synthesis__check_error__count": 0, "design__max_slew_violation__count__corner:nom_tt_025C_1v80": 0, "design__max_fanout_violation__count__corner:nom_tt_025C_1v80": 4, "design__max_cap_violation__count__corner:nom_tt_025C_1v80": 0, "power__internal__total": 7.98062319518067e-05, "power__switching__total": 3.3493539376650006e-05, "power__leakage__total": 5.0695989628479765e-09, "power__total": 0.00011330484267091379, "clock__skew__worst_hold__corner:nom_tt_025C_1v80": -1.4408004086509025, "clock__skew__worst_setup__corner:nom_tt_025C_1v80": -1.4380057551742778, "timing__hold__ws__corner:nom_tt_025C_1v80": 0.2352668959573337, "timing__setup__ws__corner:nom_tt_025C_1v80": 1.2769126117897474, "timing__hold__tns__corner:nom_tt_025C_1v80": 0, "timing__setup__tns__corner:nom_tt_025C_1v80": 0, "timing__hold__wns__corner:nom_tt_025C_1v80": 0, "timing__setup__wns__corner:nom_tt_025C_1v80": 0, "timing__hold_vio__count__corner:nom_tt_025C_1v80": 0, "timing__hold_r2r__ws__corner:nom_tt_025C_1v80": 0.235267, "timing__hold_r2r_vio__count__corner:nom_tt_025C_1v80": 0, "timing__setup_vio__count__corner:nom_tt_025C_1v80": 0, "timing__setup_r2r__ws__corner:nom_tt_025C_1v80": 1.276913, "timing__setup_r2r_vio__count__corner:nom_tt_025C_1v80": 0, "design__max_slew_violation__count__corner:nom_ss_100C_1v60": 133, "design__max_fanout_violation__count__corner:nom_ss_100C_1v60": 4, "design__max_cap_violation__count__corner:nom_ss_100C_1v60": 2, "clock__skew__worst_hold__corner:nom_ss_100C_1v60": -2.6733647163785323, "clock__skew__worst_setup__corner:nom_ss_100C_1v60": -2.6683740416970916, "timing__hold__ws__corner:nom_ss_100C_1v60": 0.6587832688053189, "timing__setup__ws__corner:nom_ss_100C_1v60": 0.17930146763716445, "timing__hold__tns__corner:nom_ss_100C_1v60": 0, "timing__setup__tns__corner:nom_ss_100C_1v60": 0, "timing__hold__wns__corner:nom_ss_100C_1v60": 0, "timing__setup__wns__corner:nom_ss_100C_1v60": 0, "timing__hold_vio__count__corner:nom_ss_100C_1v60": 0, "timing__hold_r2r__ws__corner:nom_ss_100C_1v60": 0.658783, "timing__hold_r2r_vio__count__corner:nom_ss_100C_1v60": 0, "timing__setup_vio__count__corner:nom_ss_100C_1v60": 0, "timing__setup_r2r__ws__corner:nom_ss_100C_1v60": 0.179301, "timing__setup_r2r_vio__count__corner:nom_ss_100C_1v60": 0, "design__max_slew_violation__count__corner:nom_ff_n40C_1v95": 0, "design__max_fanout_violation__count__corner:nom_ff_n40C_1v95": 4, "design__max_cap_violation__count__corner:nom_ff_n40C_1v95": 0, "clock__skew__worst_hold__corner:nom_ff_n40C_1v95": -0.7580072339913885, "clock__skew__worst_setup__corner:nom_ff_n40C_1v95": -0.7516494306387591, "timing__hold__ws__corner:nom_ff_n40C_1v95": 0.08965983764764163, "timing__setup__ws__corner:nom_ff_n40C_1v95": 1.4760041384674636, "timing__hold__tns__corner:nom_ff_n40C_1v95": 0, "timing__setup__tns__corner:nom_ff_n40C_1v95": 0, "timing__hold__wns__corner:nom_ff_n40C_1v95": 0, "timing__setup__wns__corner:nom_ff_n40C_1v95": 0, "timing__hold_vio__count__corner:nom_ff_n40C_1v95": 0, "timing__hold_r2r__ws__corner:nom_ff_n40C_1v95": 0.08966, "timing__hold_r2r_vio__count__corner:nom_ff_n40C_1v95": 0, "timing__setup_vio__count__corner:nom_ff_n40C_1v95": 0, "timing__setup_r2r__ws__corner:nom_ff_n40C_1v95": 1.476004, "timing__setup_r2r_vio__count__corner:nom_ff_n40C_1v95": 0, "design__max_slew_violation__count": 133, "design__max_fanout_violation__count": 4, "design__max_cap_violation__count": 2, "clock__skew__worst_hold": -0.7531201986322273, "clock__skew__worst_setup": -2.6765206364375875, "timing__hold__ws": 0.0810304624112335, "timing__setup__ws": 0.13265655616135494, "timing__hold__tns": 0, "timing__setup__tns": 0, "timing__hold__wns": 0, "timing__setup__wns": 0, "timing__hold_vio__count": 0, "timing__hold_r2r__ws": 0.08103, "timing__hold_r2r_vio__count": 0, "timing__setup_vio__count": 0, "timing__setup_r2r__ws": 0.132657, "timing__setup_r2r_vio__count": 0, "design__die__bbox": "0.0 0.0 108.26 118.98", "design__core__bbox": "5.52 10.88 102.58 106.08", "flow__warnings__count": 1, "flow__errors__count": 0, "design__io": 19, "design__die__area": 12880.8, "design__core__area": 9240.11, "design__instance__count__stdcell": 630, "design__instance__area__stdcell": 5187.48, "design__instance__count__macros": 0, "design__instance__area__macros": 0, "design__instance__utilization": 0.561408, "design__instance__utilization__stdcell": 0.561408, "design__power_grid_violation__count__net:vccd1": 0, "design__power_grid_violation__count__net:vssd1": 0, "design__power_grid_violation__count": 0, "floorplan__design__io": 17, "design__io__hpwl": 753874, "timing__drv__floating__nets": 0, "timing__drv__floating__pins": 0, "design__instance__displacement__total": 0, "design__instance__displacement__mean": 0, "design__instance__displacement__max": 0, "route__wirelength__estimated": 5303.48, "design__violations": 0, "design__instance__count__setup_buffer": 0, "design__instance__count__hold_buffer": 0, "antenna__violating__nets": 0, "antenna__violating__pins": 0, "route__antenna_violation__count": 0, "route__net": 370, "route__net__special": 2, "route__drc_errors__iter:1": 130, "route__wirelength__iter:1": 6208, "route__drc_errors__iter:2": 16, "route__wirelength__iter:2": 6144, "route__drc_errors__iter:3": 2, "route__wirelength__iter:3": 6121, "route__drc_errors__iter:4": 0, "route__wirelength__iter:4": 6120, "route__drc_errors": 0, "route__wirelength": 6120, "route__vias": 2459, "route__vias__singlecut": 2459, "route__vias__multicut": 0, "design__disconnected_pin__count": 0, "design__critical_disconnected_pin__count": 0, "route__wirelength__max": 640.5, "timing__unannotated_net__count__corner:nom_tt_025C_1v80": 1, "timing__unannotated_net_filtered__count__corner:nom_tt_025C_1v80": 0, "timing__unannotated_net__count__corner:nom_ss_100C_1v60": 1, "timing__unannotated_net_filtered__count__corner:nom_ss_100C_1v60": 0, "timing__unannotated_net__count__corner:nom_ff_n40C_1v95": 1, "timing__unannotated_net_filtered__count__corner:nom_ff_n40C_1v95": 0, "design__max_slew_violation__count__corner:min_tt_025C_1v80": 0, "design__max_fanout_violation__count__corner:min_tt_025C_1v80": 4, "design__max_cap_violation__count__corner:min_tt_025C_1v80": 0, "clock__skew__worst_hold__corner:min_tt_025C_1v80": -1.4329970948793294, "clock__skew__worst_setup__corner:min_tt_025C_1v80": -1.430260173001618, "timing__hold__ws__corner:min_tt_025C_1v80": 0.23730360015361046, "timing__setup__ws__corner:min_tt_025C_1v80": 1.305085854104034, "timing__hold__tns__corner:min_tt_025C_1v80": 0, "timing__setup__tns__corner:min_tt_025C_1v80": 0, "timing__hold__wns__corner:min_tt_025C_1v80": 0, "timing__setup__wns__corner:min_tt_025C_1v80": 0, "timing__hold_vio__count__corner:min_tt_025C_1v80": 0, "timing__hold_r2r__ws__corner:min_tt_025C_1v80": 0.237304, "timing__hold_r2r_vio__count__corner:min_tt_025C_1v80": 0, "timing__setup_vio__count__corner:min_tt_025C_1v80": 0, "timing__setup_r2r__ws__corner:min_tt_025C_1v80": 1.305086, "timing__setup_r2r_vio__count__corner:min_tt_025C_1v80": 0, "timing__unannotated_net__count__corner:min_tt_025C_1v80": 1, "timing__unannotated_net_filtered__count__corner:min_tt_025C_1v80": 0, "design__max_slew_violation__count__corner:min_ss_100C_1v60": 133, "design__max_fanout_violation__count__corner:min_ss_100C_1v60": 4, "design__max_cap_violation__count__corner:min_ss_100C_1v60": 2, "clock__skew__worst_hold__corner:min_ss_100C_1v60": -2.656420714142099, "clock__skew__worst_setup__corner:min_ss_100C_1v60": -2.6514122758917615, "timing__hold__ws__corner:min_ss_100C_1v60": 0.665828966363461, "timing__setup__ws__corner:min_ss_100C_1v60": 0.225847791305599, "timing__hold__tns__corner:min_ss_100C_1v60": 0, "timing__setup__tns__corner:min_ss_100C_1v60": 0, "timing__hold__wns__corner:min_ss_100C_1v60": 0, "timing__setup__wns__corner:min_ss_100C_1v60": 0, "timing__hold_vio__count__corner:min_ss_100C_1v60": 0, "timing__hold_r2r__ws__corner:min_ss_100C_1v60": 0.665829, "timing__hold_r2r_vio__count__corner:min_ss_100C_1v60": 0, "timing__setup_vio__count__corner:min_ss_100C_1v60": 0, "timing__setup_r2r__ws__corner:min_ss_100C_1v60": 0.225848, "timing__setup_r2r_vio__count__corner:min_ss_100C_1v60": 0, "timing__unannotated_net__count__corner:min_ss_100C_1v60": 1, "timing__unannotated_net_filtered__count__corner:min_ss_100C_1v60": 0, "design__max_slew_violation__count__corner:min_ff_n40C_1v95": 0, "design__max_fanout_violation__count__corner:min_ff_n40C_1v95": 4, "design__max_cap_violation__count__corner:min_ff_n40C_1v95": 0, "clock__skew__worst_hold__corner:min_ff_n40C_1v95": -0.7531201986322273, "clock__skew__worst_setup__corner:min_ff_n40C_1v95": -0.7468390006704637, "timing__hold__ws__corner:min_ff_n40C_1v95": 0.0923467994878319, "timing__setup__ws__corner:min_ff_n40C_1v95": 1.49505512201962, "timing__hold__tns__corner:min_ff_n40C_1v95": 0, "timing__setup__tns__corner:min_ff_n40C_1v95": 0, "timing__hold__wns__corner:min_ff_n40C_1v95": 0, "timing__setup__wns__corner:min_ff_n40C_1v95": 0, "timing__hold_vio__count__corner:min_ff_n40C_1v95": 0, "timing__hold_r2r__ws__corner:min_ff_n40C_1v95": 0.092347, "timing__hold_r2r_vio__count__corner:min_ff_n40C_1v95": 0, "timing__setup_vio__count__corner:min_ff_n40C_1v95": 0, "timing__setup_r2r__ws__corner:min_ff_n40C_1v95": 1.495055, "timing__setup_r2r_vio__count__corner:min_ff_n40C_1v95": 0, "timing__unannotated_net__count__corner:min_ff_n40C_1v95": 1, "timing__unannotated_net_filtered__count__corner:min_ff_n40C_1v95": 0, "design__max_slew_violation__count__corner:max_tt_025C_1v80": 0, "design__max_fanout_violation__count__corner:max_tt_025C_1v80": 4, "design__max_cap_violation__count__corner:max_tt_025C_1v80": 0, "clock__skew__worst_hold__corner:max_tt_025C_1v80": -1.4407666578699994, "clock__skew__worst_setup__corner:max_tt_025C_1v80": -1.437999537925164, "timing__hold__ws__corner:max_tt_025C_1v80": 0.2269493823773628, "timing__setup__ws__corner:max_tt_025C_1v80": 1.244894444987837, "timing__hold__tns__corner:max_tt_025C_1v80": 0, "timing__setup__tns__corner:max_tt_025C_1v80": 0, "timing__hold__wns__corner:max_tt_025C_1v80": 0, "timing__setup__wns__corner:max_tt_025C_1v80": 0, "timing__hold_vio__count__corner:max_tt_025C_1v80": 0, "timing__hold_r2r__ws__corner:max_tt_025C_1v80": 0.226949, "timing__hold_r2r_vio__count__corner:max_tt_025C_1v80": 0, "timing__setup_vio__count__corner:max_tt_025C_1v80": 0, "timing__setup_r2r__ws__corner:max_tt_025C_1v80": 1.244895, "timing__setup_r2r_vio__count__corner:max_tt_025C_1v80": 0, "timing__unannotated_net__count__corner:max_tt_025C_1v80": 1, "timing__unannotated_net_filtered__count__corner:max_tt_025C_1v80": 0, "design__max_slew_violation__count__corner:max_ss_100C_1v60": 133, "design__max_fanout_violation__count__corner:max_ss_100C_1v60": 4, "design__max_cap_violation__count__corner:max_ss_100C_1v60": 2, "clock__skew__worst_hold__corner:max_ss_100C_1v60": -2.681500208888468, "clock__skew__worst_setup__corner:max_ss_100C_1v60": -2.6765206364375875, "timing__hold__ws__corner:max_ss_100C_1v60": 0.6464445828275804, "timing__setup__ws__corner:max_ss_100C_1v60": 0.13265655616135494, "timing__hold__tns__corner:max_ss_100C_1v60": 0, "timing__setup__tns__corner:max_ss_100C_1v60": 0, "timing__hold__wns__corner:max_ss_100C_1v60": 0, "timing__setup__wns__corner:max_ss_100C_1v60": 0, "timing__hold_vio__count__corner:max_ss_100C_1v60": 0, "timing__hold_r2r__ws__corner:max_ss_100C_1v60": 0.646445, "timing__hold_r2r_vio__count__corner:max_ss_100C_1v60": 0, "timing__setup_vio__count__corner:max_ss_100C_1v60": 0, "timing__setup_r2r__ws__corner:max_ss_100C_1v60": 0.132657, "timing__setup_r2r_vio__count__corner:max_ss_100C_1v60": 0, "timing__unannotated_net__count__corner:max_ss_100C_1v60": 1, "timing__unannotated_net_filtered__count__corner:max_ss_100C_1v60": 0, "design__max_slew_violation__count__corner:max_ff_n40C_1v95": 0, "design__max_fanout_violation__count__corner:max_ff_n40C_1v95": 4, "design__max_cap_violation__count__corner:max_ff_n40C_1v95": 0, "clock__skew__worst_hold__corner:max_ff_n40C_1v95": -0.7557563677676046, "clock__skew__worst_setup__corner:max_ff_n40C_1v95": -0.7493270660501672, "timing__hold__ws__corner:max_ff_n40C_1v95": 0.0810304624112335, "timing__setup__ws__corner:max_ff_n40C_1v95": 1.4526252833983129, "timing__hold__tns__corner:max_ff_n40C_1v95": 0, "timing__setup__tns__corner:max_ff_n40C_1v95": 0, "timing__hold__wns__corner:max_ff_n40C_1v95": 0, "timing__setup__wns__corner:max_ff_n40C_1v95": 0, "timing__hold_vio__count__corner:max_ff_n40C_1v95": 0, "timing__hold_r2r__ws__corner:max_ff_n40C_1v95": 0.08103, "timing__hold_r2r_vio__count__corner:max_ff_n40C_1v95": 0, "timing__setup_vio__count__corner:max_ff_n40C_1v95": 0, "timing__setup_r2r__ws__corner:max_ff_n40C_1v95": 1.452625, "timing__setup_r2r_vio__count__corner:max_ff_n40C_1v95": 0, "timing__unannotated_net__count__corner:max_ff_n40C_1v95": 1, "timing__unannotated_net_filtered__count__corner:max_ff_n40C_1v95": 0, "timing__unannotated_net__count": 1, "timing__unannotated_net_filtered__count": 0, "design_powergrid__voltage__worst__net:vccd1__corner:nom_tt_025C_1v80": 1.79998, "design_powergrid__drop__average__net:vccd1__corner:nom_tt_025C_1v80": 1.8, "design_powergrid__drop__worst__net:vccd1__corner:nom_tt_025C_1v80": 1.7027e-05, "design_powergrid__voltage__worst__net:vssd1__corner:nom_tt_025C_1v80": 1.41573e-05, "design_powergrid__drop__average__net:vssd1__corner:nom_tt_025C_1v80": 2.41021e-06, "design_powergrid__drop__worst__net:vssd1__corner:nom_tt_025C_1v80": 1.41573e-05, "ir__voltage__worst": 1.8, "ir__drop__avg": 2.46e-06, "ir__drop__worst": 1.7e-05, "design__xor_difference__count": 0, "magic__drc_error__count": 0, "klayout__drc_error__count": 0, "magic__illegal_overlap__count": 0, "design__lvs_device_difference__count": 0, "design__lvs_net_difference__count": 0, "design__lvs_property_fail__count": 0, "design__lvs_error__count": 0, "design__lvs_unmatched_device__count": 0, "design__lvs_unmatched_net__count": 0, "design__lvs_unmatched_pin__count": 0}